rest_mediabrowser/__init__.py
rest_mediabrowser/admin.py
rest_mediabrowser/appconfig.py
rest_mediabrowser/apps.py
rest_mediabrowser/models.py
rest_mediabrowser/paginations.py
rest_mediabrowser/permissions.py
rest_mediabrowser/serializers.py
rest_mediabrowser/specs.py
rest_mediabrowser/tests.py
rest_mediabrowser/urls.py
rest_mediabrowser/utils.py
rest_mediabrowser/views.py
rest_mediabrowser/migrations/0001_initial.py
rest_mediabrowser/migrations/0002_auto_20201125_0939.py
rest_mediabrowser/migrations/0003_auto_20201130_0405.py
rest_mediabrowser/migrations/0004_auto_20201220_0746.py
rest_mediabrowser/migrations/__init__.py
rest_mediabrowser/testfiles/1.png
rest_mediabrowser/testfiles/demo.pdf
django_rest_mediabrowser-0.12.0.dist-info/LICENSE
django_rest_mediabrowser-0.12.0.dist-info/METADATA
django_rest_mediabrowser-0.12.0.dist-info/WHEEL
django_rest_mediabrowser-0.12.0.dist-info/top_level.txt
django_rest_mediabrowser-0.12.0.dist-info/RECORD
