Metadata-Version: 2.1
Name: django-rest-mediabrowser
Version: 0.12.0
Summary: A File Browser for REST API.
Home-page: https://gitlab.com/codesigntheory/django-rest-mediabrowser
Author: Utsob Roy
Author-email: roy@codesign.com.bd
License: Mozilla Public License 2.0 (MPL 2.0)
Classifier: Environment :: Web Environment
Classifier: Framework :: Django
Classifier: Framework :: Django :: 2.0
Classifier: Intended Audience :: Developers
Classifier: License :: OSI Approved :: Mozilla Public License 2.0 (MPL 2.0)
Classifier: Operating System :: OS Independent
Classifier: Programming Language :: Python
Classifier: Programming Language :: Python :: 3.5
Classifier: Programming Language :: Python :: 3.6
Classifier: Topic :: Internet :: WWW/HTTP
Classifier: Topic :: Internet :: WWW/HTTP :: Dynamic Content
License-File: LICENSE
Requires-Dist: djangorestframework
Requires-Dist: pillow
Requires-Dist: django-private-storage
Requires-Dist: django-taggit
Requires-Dist: django-taggit-serializer
Requires-Dist: django-filter
Requires-Dist: django-imagekit
